{
    "gid": "RoadStructure.LANE",
    "description": "RoadStructure_LANE",
    "direction": "left",
    "roads": [
        {
            "id": "R100",
            "length": 100,
            "height": 0,
            "ramp_angle": 0,
            "type": "straight",
            "radius": 80,
            "start_radius": 0,
            "end_radius": 0,
            "reverse": false,
            "connectionInfo": {
                "world": {
                    "position": {
                        "x": 0,
                        "y": 0,
                        "z": 0
                    },
                    "rotation": {
                        "_x": 0,
                        "_y": 0,
                        "_z": 0,
                        "_order": "XYZ"
                    }
                },
                "positive": {
                    "position": {
                        "x": 0,
                        "y": 0,
                        "z": 0
                    },
                    "rotation": {
                        "_x": 0,
                        "_y": 0,
                        "_z": 0,
                        "_order": "XYZ"
                    }
                },
                "negative": {
                    "position": {
                        "x": 0,
                        "y": 0,
                        "z": 0
                    },
                    "rotation": {
                        "_x": 0,
                        "_y": 0,
                        "_z": 0,
                        "_order": "XYZ"
                    }
                },
                "to": {}
            },
            "lanes": {
                "left": [
                    {
                        "id": "L105",
                        "type": "sidewalk",
                        "position": "left",
                        "width": 5,
                        "refLineVisible": false
                    },
                    {
                        "id": "L104",
                        "type": "border",
                        "position": "left",
                        "width": 1.5,
                        "refLineVisible": false
                    },
                    {
                        "id": "L103",
                        "type": "driving",
                        "position": "left",
                        "width": 3.5,
                        "refLineVisible": false
                    },
                    {
                        "id": "L102",
                        "type": "driving",
                        "position": "left",
                        "width": 3.5,
                        "refLineVisible": false
                    }
                ],
                "center": [
                    {
                        "id": "L101",
                        "type": "center",
                        "position": "center",
                        "width": 1,
                        "refLineVisible": false
                    }
                ],
                "right": [
                    {
                        "id": "L106",
                        "type": "driving",
                        "position": "right",
                        "width": 3.5,
                        "refLineVisible": false
                    },
                    {
                        "id": "L107",
                        "type": "driving",
                        "position": "right",
                        "width": 3.5,
                        "refLineVisible": false
                    },
                    {
                        "id": "L108",
                        "type": "border",
                        "position": "right",
                        "width": 1.5,
                        "refLineVisible": false
                    },
                    {
                        "id": "L109",
                        "type": "sidewalk",
                        "position": "right",
                        "width": 5,
                        "refLineVisible": false
                    }
                ]
            },
            "refLineVisible": false,
            "priorityRoad": false,
            "point": {
                "x": 0,
                "y": 0,
                "z": 0,
                "roll": 0,
                "yaw": 0,
                "pitch": 0
            }
        }
    ],
    "junctions": [],
    "objects": [],
    "trajectories": [],
    "backgroundPlane01": {
        "metadata": {
            "version": 4.5,
            "type": "Object",
            "generator": "Object3D.toJSON"
        },
        "geometries": [
            {
                "uuid": "741415BA-AA6C-48B6-9FB1-C1DC293964FF",
                "type": "PlaneBufferGeometry",
                "width": 0,
                "height": 0,
                "widthSegments": 1,
                "heightSegments": 1
            }
        ],
        "materials": [
            {
                "uuid": "90591BEB-DCFF-49FA-8F6C-5716CE77C90B",
                "type": "MeshStandardMaterial",
                "color": 15790320,
                "roughness": 1,
                "metalness": 0,
                "emissive": 0,
                "depthFunc": 3,
                "depthTest": true,
                "depthWrite": true,
                "stencilWrite": false,
                "stencilWriteMask": 255,
                "stencilFunc": 519,
                "stencilRef": 0,
                "stencilFuncMask": 255,
                "stencilFail": 7680,
                "stencilZFail": 7680,
                "stencilZPass": 7680
            }
        ],
        "object": {
            "uuid": "20E8CD0D-5BF5-44A8-8261-E524E5F8DCFF",
            "type": "Mesh",
            "visible": false,
            "layers": 1,
            "matrix": [
                1,
                0,
                0,
                0,
                0,
                1,
                0,
                0,
                0,
                0,
                1,
                0,
                0,
                -50,
                0,
                1
            ],
            "geometry": "741415BA-AA6C-48B6-9FB1-C1DC293964FF",
            "material": "90591BEB-DCFF-49FA-8F6C-5716CE77C90B"
        }
    },
    "backgroundPlane02": {
        "metadata": {
            "version": 4.5,
            "type": "Object",
            "generator": "Object3D.toJSON"
        },
        "geometries": [
            {
                "uuid": "E0FEBEAB-83D4-4316-AA9F-7768AA5B98AB",
                "type": "PlaneBufferGeometry",
                "width": 0,
                "height": 0,
                "widthSegments": 1,
                "heightSegments": 1
            }
        ],
        "materials": [
            {
                "uuid": "461D4560-0ED1-404C-919E-33655B134887",
                "type": "MeshStandardMaterial",
                "color": 15790320,
                "roughness": 1,
                "metalness": 0,
                "emissive": 0,
                "depthFunc": 3,
                "depthTest": true,
                "depthWrite": true,
                "stencilWrite": false,
                "stencilWriteMask": 255,
                "stencilFunc": 519,
                "stencilRef": 0,
                "stencilFuncMask": 255,
                "stencilFail": 7680,
                "stencilZFail": 7680,
                "stencilZPass": 7680
            }
        ],
        "object": {
            "uuid": "9DC666AD-9CD5-44E4-81F6-3B097889A151",
            "type": "Mesh",
            "visible": false,
            "layers": 1,
            "matrix": [
                1,
                0,
                0,
                0,
                0,
                1,
                0,
                0,
                0,
                0,
                1,
                0,
                0,
                -50,
                0,
                1
            ],
            "geometry": "E0FEBEAB-83D4-4316-AA9F-7768AA5B98AB",
            "material": "461D4560-0ED1-404C-919E-33655B134887"
        }
    }
}